Metadata-Version: 2.1
Name: test-f-meliq
Version: 0.0.1
Summary: It,s test Description
Author: Meliq
License-File: LICENSE
